{
  "kind": "singleType",
  "collectionName": "contacts",
  "info": {
    "singularName": "contact",
    "pluralName": "contacts",
    "displayName": "Contact"
  },
  "options": {
    "draftAndPublish": true
  },
  "pluginOptions": {},
  "attributes": {
    "contact_cover_title": {
      "type": "string"
    },
    "contact_cover": {
      "allowedTypes": [
        "images",
        "files",
        "videos",
        "audios"
      ],
      "type": "media",
      "multiple": false
    },
    "contact_cover_subtitle": {
      "type": "string"
    },
    "contact_content_title": {
      "type": "string"
    },
    "contact_address_title": {
      "type": "string"
    },
    "contact_email_title": {
      "type": "string"
    },
    "contact_phone_title": {
      "type": "string"
    },
    "contact_address_icon": {
      "allowedTypes": [
        "images",
        "files",
        "videos",
        "audios"
      ],
      "type": "media",
      "multiple": false
    },
    "contact_email_icon": {
      "allowedTypes": [
        "images",
        "files",
        "videos",
        "audios"
      ],
      "type": "media",
      "multiple": false
    },
    "contact_phone_icon": {
      "allowedTypes": [
        "images",
        "files",
        "videos",
        "audios"
      ],
      "type": "media",
      "multiple": false
    },
    "contact_address": {
      "type": "string"
    },
    "contact_email": {
      "type": "string"
    },
    "contact_phone": {
      "type": "string"
    }
  }
}
